{"cameraMode":{"drawMode":0,"name":"Shaded","section":"Shading Mode"},"sceneLighting":true,"audioPlay":false,"sceneViewState":{"showFog":true,"showMaterialUpdate":false,"showSkybox":true,"showFlares":true,"showImageEffects":true,"showParticleSystems":true,"showVisualEffectGraphs":true,"m_FxEnabled":true},"in2DMode":false,"pivot":{"x":260.8385009765625,"y":757.2515258789063,"z":-1639.8404541015625},"rotation":{"x":-0.24564167857170106,"y":-0.13844060897827149,"z":0.03546915203332901,"w":-0.9587700963020325},"size":373.5174560546875,"orthographic":false}